tracklist2playlist/__init__.py
tracklist2playlist/main.py
tracklist2playlist/spotitools.py
tracklist2playlist_sources/__init__.py
tracklist2playlist_sources/livetracklist.py
tracklist2playlist_sources/thousandonetracklists.py
tracklist2playlist-0.1.dist-info/LICENSE
tracklist2playlist-0.1.dist-info/METADATA
tracklist2playlist-0.1.dist-info/WHEEL
tracklist2playlist-0.1.dist-info/entry_points.txt
tracklist2playlist-0.1.dist-info/top_level.txt
tracklist2playlist-0.1.dist-info/RECORD
