Metadata-Version: 2.1
Name: tracklist2playlist
Version: 0.1
Summary: converts the tracklists to spotify playlists
Home-page: https://www.github.com/raprocks/tracklist2playlist
Author: Rohit Patil
Author-email: rahulhimesh09@gmail.com
License: MIT
Platform: UNKNOWN
Classifier: License :: OSI Approved :: MIT License
Classifier: Programming Language :: Python :: 3
Classifier: Programming Language :: Python :: 3 :: Only
Classifier: Programming Language :: Python :: 3.6
Classifier: Programming Language :: Python :: 3.7
Classifier: Programming Language :: Python :: 3.8
Classifier: Programming Language :: Python :: 3.9
Classifier: Topic :: Multimedia :: Sound/Audio
Classifier: Development Status :: 5 - Production/Stable
Classifier: Environment :: Console
Requires-Dist: spotipy
Requires-Dist: requests
Requires-Dist: bs4
Requires-Dist: click
